clickhouse_migrate/__init__.py
clickhouse_migrate/migrate.py
clickhouse_migrator-1.0.6.dist-info/LICENSE
clickhouse_migrator-1.0.6.dist-info/METADATA
clickhouse_migrator-1.0.6.dist-info/WHEEL
clickhouse_migrator-1.0.6.dist-info/top_level.txt
clickhouse_migrator-1.0.6.dist-info/RECORD
