Metadata-Version: 2.1
Name: clickhouse-migrator
Version: 1.0.6
Summary: Migration library for Clickhouse
Home-page: https://github.com/delium/clickhouse-migrator
Author: Delium Engineering
Author-email: oss@delium.co
License: MIT
Platform: UNKNOWN
Requires-Python: >=3.6
License-File: LICENSE
Requires-Dist: pandas
Requires-Dist: clickhouse-driver
